pytest_ranking/__init__.py
pytest_ranking/change_tracker.py
pytest_ranking/const.py
pytest_ranking/plugin.py
pytest_ranking/rank.py
pytest_ranking-0.3.4.dist-info/licenses/LICENSE
pytest_ranking-0.3.4.dist-info/METADATA
pytest_ranking-0.3.4.dist-info/WHEEL
pytest_ranking-0.3.4.dist-info/entry_points.txt
pytest_ranking-0.3.4.dist-info/top_level.txt
pytest_ranking-0.3.4.dist-info/RECORD
